ssw_py-1.0.1.dist-info/RECORD
ssw_py-1.0.1.dist-info/WHEEL
ssw_py-1.0.1.dist-info/METADATA
ssw_py-1.0.1.dist-info/LICENSE.md
ssw_py-1.0.1.dist-info/top_level.txt
ssw/alignmenttuple.py
ssw/printer.py
ssw/alignmentmgr.cpython-311-x86_64-linux-gnu.so
ssw/__init__.py
ssw/lib/str_util.h
ssw/lib/str_util.c
ssw/lib/CSSWL/README.md
ssw/lib/CSSWL/src/sse2neon.h
ssw/lib/CSSWL/src/kseq.h
ssw/lib/CSSWL/src/ssw_cpp.h
ssw/lib/CSSWL/src/example.c
ssw/lib/CSSWL/src/Makefile
ssw/lib/CSSWL/src/ssw_cpp.cpp
ssw/lib/CSSWL/src/ssw.c
ssw/lib/CSSWL/src/main.c
ssw/lib/CSSWL/src/ssw.h
ssw/lib/CSSWL/src/example.cpp
tests/test_ssw.py
tests/__init__.py
