Metadata-Version: 2.1
Name: ssw-py
Version: 1.0.1
Summary: Python bindings for Complete-Striped-Smith-Waterman-Library (SSW) project
Home-page: https://github.com/libnano/ssw-py
Author: Nick Conway
Author-email: a.grinner@gmail.com
License: MIT
Classifier: Development Status :: 5 - Production/Stable
Classifier: Environment :: Console
Classifier: Intended Audience :: Science/Research
Classifier: Programming Language :: Python
Classifier: Programming Language :: Python :: 3
Classifier: Programming Language :: Cython
Classifier: Topic :: Scientific/Engineering
License-File: LICENSE.md
